INSTALL.md
MANIFEST.in
README.md
algoinject.py
setup.cfg
setup.py
start-algo.sh
stop-algo.sh
algobroker/__init__.py
algobroker/broker_bitmex.py
algobroker/broker_plivo.py
algobroker/broker_twilio.py
algobroker/broker_web.py
algobroker/dispatcher.py
algobroker/my_path.py
algobroker/strategy_alert.py
algobroker/strategy_xbt_close.py
algobroker/ticker_bitcoin.py
algobroker/ticker_yahoo.py
algobroker.egg-info/PKG-INFO
algobroker.egg-info/SOURCES.txt
algobroker.egg-info/dependency_links.txt
algobroker.egg-info/requires.txt
algobroker.egg-info/top_level.txt
algobroker/static/broker_reactjs.html
algobroker/static/broker_reactjs.js
algobroker/static/broker_web.html
algobroker/static/broker_web.js
algobroker/static/high.ogg
algobroker/static/low.ogg
algobroker/static/ui-bootstrap-tpls-0.14.3.min.js
algobroker/static/ui-grid.min.js
algobroker/static/ui-grid.ttf
algobroker/static/ui-grid.woff
algobroker/test/bitmex.py
algobroker/test/control.py
algobroker/test/helloworld.py
algobroker/test/ping_monitor.py
cmds/debug.json
cmds/example.json