Metadata-Version: 1.0
Name: algobroker
Version: 0.0.12
Summary: Algorithmic trading broker
Home-page: https://github.com/joequant/algobroker
Author: Joseph C Wang
Author-email: joequant@gmail.com
License: BSD
Platform: UNKNOWN
